pyharmx/__init__.py
pyharmx/functions.py
pyharmx/interpolator.py
tests/__init__.py
tests/test_interpolator.py
pyharmx-0.1.5.dist-info/LICENSE
pyharmx-0.1.5.dist-info/METADATA
pyharmx-0.1.5.dist-info/WHEEL
pyharmx-0.1.5.dist-info/top_level.txt
pyharmx-0.1.5.dist-info/RECORD
