Metadata-Version: 2.1
Name: pyharmx
Version: 0.1.5
Summary: Polyharmonic spline interpolation in PyTorch
Author-email: Ivan Zanardi <ivan.zanardi.us@gmail.com>
License: MIT License
Project-URL: Homepage, https://github.com/ivanZanardi/pyharmx
Project-URL: Bug Tracker, https://github.com/ivanZanardi/pyharmx/issues
Project-URL: Changelog, https://github.com/ivanZanardi/pyharmx/releases
Project-URL: Documentation, https://pyharmx.readthedocs.io
Keywords: Python,PyTorch,Interpolation,Spline,Polyharmonic Spline,RBF,Radial Basis Function
Classifier: Development Status :: 4 - Beta
Classifier: Intended Audience :: Developers
Classifier: Intended Audience :: Education
Classifier: Intended Audience :: Science/Research
Classifier: License :: OSI Approved :: MIT License
Classifier: Programming Language :: Python :: 3
Classifier: Topic :: Scientific/Engineering
Classifier: Topic :: Scientific/Engineering :: Mathematics
Classifier: Topic :: Software Development :: Libraries
Classifier: Topic :: Software Development :: Libraries :: Python Modules
Requires-Python: >=3.8
License-File: LICENSE
Requires-Dist: numpy
Requires-Dist: typing
Requires-Dist: torch
Provides-Extra: test
Requires-Dist: pytest; extra == "test"
